manage.py
Kipkoech_polls-0.2.5.dist-info/LICENSE
Kipkoech_polls-0.2.5.dist-info/METADATA
Kipkoech_polls-0.2.5.dist-info/WHEEL
Kipkoech_polls-0.2.5.dist-info/top_level.txt
Kipkoech_polls-0.2.5.dist-info/RECORD
